brian2tools/__init__.py
brian2tools/baseexport/__init__.py
brian2tools/baseexport/collector.py
brian2tools/baseexport/device.py
brian2tools/baseexport/helper.py
brian2tools/mdexport/__init__.py
brian2tools/mdexport/expander.py
brian2tools/mdexport/mdexporter.py
brian2tools/nmlexport/LEMSUnitsConstants.xml
brian2tools/nmlexport/NeuroMLCoreDimensions.xml
brian2tools/nmlexport/__init__.py
brian2tools/nmlexport/lemsexport.py
brian2tools/nmlexport/lemsrendering.py
brian2tools/nmlexport/supporting.py
brian2tools/nmlimport/__init__.py
brian2tools/nmlimport/helper.py
brian2tools/nmlimport/nml.py
brian2tools/nmlutils/__init__.py
brian2tools/nmlutils/utils.py
brian2tools/plotting/__init__.py
brian2tools/plotting/base.py
brian2tools/plotting/data.py
brian2tools/plotting/morphology.py
brian2tools/plotting/synapses.py
brian2tools/tests/__init__.py
brian2tools/tests/testScript.py
brian2tools/tests/test_baseexport.py
brian2tools/tests/test_mdexport.py
brian2tools/tests/test_nmlexport.py
brian2tools/tests/test_nmlimport.py
brian2tools/tests/test_plotting.py
brian2tools/tests/samples/sample1.cell.nml
brian2tools-0.3.dist-info/LICENSE
brian2tools-0.3.dist-info/METADATA
brian2tools-0.3.dist-info/WHEEL
brian2tools-0.3.dist-info/top_level.txt
brian2tools-0.3.dist-info/RECORD
