Metadata-Version: 2.1
Name: brian2tools
Version: 0.3
Summary: Tools for the Brian 2 simulator
Home-page: https://github.com/brian-team/brian2tools
Author: Marcel Stimberg, Dan Goodman, Romain Brette
Author-email: team@briansimulator.org
License: CeCILL-2.1
Keywords: visualization neuroscience
Platform: UNKNOWN
Classifier: Development Status :: 4 - Beta
Classifier: Intended Audience :: Science/Research
Classifier: License :: OSI Approved :: CEA CNRS Inria Logiciel Libre License, version 2.1 (CeCILL-2.1)
Classifier: Natural Language :: English
Classifier: Operating System :: OS Independent
Classifier: Programming Language :: Python
Classifier: Programming Language :: Python :: 3
Classifier: Topic :: Scientific/Engineering :: Bio-Informatics
Provides: brian2tools
Requires-Python: >=3.5
Requires-Dist: matplotlib (>=1.3.1)
Requires-Dist: brian2 (>=2.0)
Requires-Dist: setuptools
Requires-Dist: setuptools-scm
Requires-Dist: pylems (>=0.4.9)
Requires-Dist: libNeuroML (>=0.2.18)
Requires-Dist: markdown-strings
Provides-Extra: docs
Requires-Dist: sphinx (>=1.7) ; extra == 'docs'
Provides-Extra: test
Requires-Dist: pytest ; extra == 'test'
